[
  {
    "Title": "BẮC BLING (BẮC NINH) | OFFICIAL MV | HOÀ MINZY ft NS XUÂN HINH x MASEW x TUẤN CRY",
    "Channel": "Hòa Minzy",
    "Views": "106714258",
    "URL": "https://www.youtube.com/watch?v=CL13X-8o4h0",
    "Image": "https://i.ytimg.com/vi/CL13X-8o4h0/hqdefault.jpg",
    "ViewHistory": [
      106714258,
      106714258
    ]
  },
  {
    "Title": "SOOBIN - Dancing In The Dark | 'BẬT NÓ LÊN' Album (Official MV)",
    "Channel": "SOOBIN Official",
    "Views": "8221164",
    "URL": "https://www.youtube.com/watch?v=OZmK0YuSmXU",
    "Image": "https://i.ytimg.com/vi/OZmK0YuSmXU/hqdefault.jpg",
    "ViewHistory": [
      8221163,
      8221164
    ]
  },
  {
    "Title": "LỄ ĐƯỜNG của Hải Long & Salim | KAI ĐINH | Official MV",
    "Channel": "Kai Dinh Official",
    "Views": "2129862",
    "URL": "https://www.youtube.com/watch?v=XqgyD0yadH0",
    "Image": "https://i.ytimg.com/vi/XqgyD0yadH0/hqdefault.jpg",
    "ViewHistory": [
      2129852,
      2129862
    ]
  },
  {
    "Title": "[XHTDRLX3] Yêu Một Người Sao Buồn Đến Thế - Noo Phước Thịnh, Anh Tú “over hợp” trong lần đầu kết hợp",
    "Channel": "FOREST STUDIO",
    "Views": "1575641",
    "URL": "https://www.youtube.com/watch?v=WOZ85j3DqGs",
    "Image": "https://i.ytimg.com/vi/WOZ85j3DqGs/hqdefault.jpg",
    "ViewHistory": [
      1575636,
      1575641
    ]
  },
  {
    "Title": "[ KARAOKE BEAT CHUẨN ] BẮC BLING ( BẮC NINH ) - HOÀ MINZY FT NS XUÂN HINH x MASEW x TUẤN CRY",
    "Channel": "Hòa Minzy",
    "Views": "6952589",
    "URL": "https://www.youtube.com/watch?v=GAc_G1tonwg",
    "Image": "https://i.ytimg.com/vi/GAc_G1tonwg/hqdefault.jpg",
    "ViewHistory": [
      6952370,
      6952589
    ]
  },
  {
    "Title": "ERIK - 'Dù cho tận thế (vẫn yêu em)' (Wedding Version) | Live at LimLong's Wedding",
    "Channel": "ERIK Official",
    "Views": "2815506",
    "URL": "https://www.youtube.com/watch?v=_-Z8qK7tnWY",
    "Image": "https://i.ytimg.com/vi/_-Z8qK7tnWY/hqdefault.jpg",
    "ViewHistory": [
      2815503,
      2815506
    ]
  },
  {
    "Title": "[XHTDRLX3] Những Kẻ Mộng Mơ - Noo Phước Thịnh x Lâm Bảo Ngọc \"tái sinh\" ca khúc vạn người mê",
    "Channel": "FOREST STUDIO",
    "Views": "496207",
    "URL": "https://www.youtube.com/watch?v=vC9v-pbJRGE",
    "Image": "https://i.ytimg.com/vi/vC9v-pbJRGE/hqdefault.jpg",
    "ViewHistory": [
      496301,
      496207
    ]
  },
  {
    "Title": "JENNIE - like JENNIE (Official Video)",
    "Channel": "JennieRubyJaneVEVO",
    "Views": "54629937",
    "URL": "https://www.youtube.com/watch?v=JSFG-IE8n_c",
    "Image": "https://i.ytimg.com/vi/JSFG-IE8n_c/hqdefault.jpg",
    "ViewHistory": [
      54629934,
      54629937
    ]
  },
  {
    "Title": "Sự Nghiệp Chướng - Pháo「Cukak Remix」/ Audio Lyrics Video",
    "Channel": "Cukak",
    "Views": "607270",
    "URL": "https://www.youtube.com/watch?v=U0-Mfc5ijkQ",
    "Image": "https://i.ytimg.com/vi/U0-Mfc5ijkQ/hqdefault.jpg",
    "ViewHistory": [
      607265,
      607270
    ]
  },
  {
    "Title": "Bậu Ơi Đừng Khóc - Hồng Loan, Hồng Ny, Tuyết Ngọc | Official Music Video",
    "Channel": "VŨ LINH FAMILY",
    "Views": "606387",
    "URL": "https://www.youtube.com/watch?v=8kC_ZOPG3qc",
    "Image": "https://i.ytimg.com/vi/8kC_ZOPG3qc/hqdefault.jpg",
    "ViewHistory": [
      606331,
      606387
    ]
  },
  {
    "Title": "EM MUỐN TỰ DO  - Du Uyên x Thưởng | OFFICIAL VISUALIZER",
    "Channel": "Du Uyên",
    "Views": "819244",
    "URL": "https://www.youtube.com/watch?v=-bN29j4It_8",
    "Image": "https://i.ytimg.com/vi/-bN29j4It_8/hqdefault.jpg",
    "ViewHistory": [
      819012,
      819244
    ]
  },
  {
    "Title": "Câu Trả Lời",
    "Channel": "J.Ade - Topic",
    "Views": "3133877",
    "URL": "https://www.youtube.com/watch?v=X_jpwMx8bBM",
    "Image": "https://i.ytimg.com/vi/X_jpwMx8bBM/hqdefault.jpg",
    "ViewHistory": [
      3133868,
      3133877
    ]
  },
  {
    "Title": "ĐÃ LÂU RỒI - NEGAV",
    "Channel": "Negav",
    "Views": "1760581",
    "URL": "https://www.youtube.com/watch?v=8WHfAozUx38",
    "Image": "https://i.ytimg.com/vi/8WHfAozUx38/hqdefault.jpg",
    "ViewHistory": [
      1760577,
      1760581
    ]
  },
  {
    "Title": "Sự Nghiệp Chướng Remix (Bản Chiến Nhất TikTok) - Pháo x NamNguyen x H2O",
    "Channel": "H2O Remix",
    "Views": "607263",
    "URL": "https://www.youtube.com/watch?v=Lp03t-QFN_0",
    "Image": "https://i.ytimg.com/vi/Lp03t-QFN_0/hqdefault.jpg",
    "ViewHistory": [
      607112,
      607263
    ]
  },
  {
    "Title": "Hoang Tưởng Đêm Khuya (Theme Song From \"Quỷ Nhập Tràng\") | Lyrics Video",
    "Channel": "VIEENT Music",
    "Views": "813852",
    "URL": "https://www.youtube.com/watch?v=LJwUT_n_D5k",
    "Image": "https://i.ytimg.com/vi/LJwUT_n_D5k/hqdefault.jpg",
    "ViewHistory": [
      813852,
      813852
    ]
  },
  {
    "Title": "Em Muốn Tự Do x Sự Nghiệp Chướng - Du Uyên x Pháo x Domino Remix | Em Muốn Tự Do Anh Ơi Remix",
    "Channel": "ACV Entertainment",
    "Views": "403242",
    "URL": "https://www.youtube.com/watch?v=saxAzkv0ZQ0",
    "Image": "https://i.ytimg.com/vi/saxAzkv0ZQ0/hqdefault.jpg",
    "ViewHistory": [
      403241,
      403242
    ]
  },
  {
    "Title": "Địa Đàng - Hoàng Oanh x CaoTri | Official Lofi Lyrics",
    "Channel": "CaoTri Official ",
    "Views": "1175451",
    "URL": "https://www.youtube.com/watch?v=vvdTwjpc3JM",
    "Image": "https://i.ytimg.com/vi/vvdTwjpc3JM/hqdefault.jpg",
    "ViewHistory": [
      1175447,
      1175451
    ]
  },
  {
    "Title": "DÀNH CHO CON - KHẢ HIỆP I OFFICIAL MV | Con của cha ngoan nhé mau lớn khôn và trưởng thành…",
    "Channel": "KHẢ HIỆP Official",
    "Views": "629651",
    "URL": "https://www.youtube.com/watch?v=mpmwaqYdr7M",
    "Image": "https://i.ytimg.com/vi/mpmwaqYdr7M/hqdefault.jpg",
    "ViewHistory": [
      629596,
      629651
    ]
  },
  {
    "Title": "LỄ ĐƯỜNG - KAI DINH | từ câu chuyện của SALIM và HẢI LONG | Journey Version",
    "Channel": "Kai Dinh Official",
    "Views": "1310286",
    "URL": "https://www.youtube.com/watch?v=LMpWNZ_M64g",
    "Image": "https://i.ytimg.com/vi/LMpWNZ_M64g/hqdefault.jpg",
    "ViewHistory": [
      1310284,
      1310286
    ]
  },
  {
    "Title": "[XHTDRLX3] Ánh Sao Và Bầu Trời - Noo Phước Thịnh thổi làn gió mới vào bản HIT của T.R.I x Cá",
    "Channel": "FOREST STUDIO",
    "Views": "338998",
    "URL": "https://www.youtube.com/watch?v=MOYRrs_Mv20",
    "Image": "https://i.ytimg.com/vi/MOYRrs_Mv20/hqdefault.jpg",
    "ViewHistory": [
      338780,
      338998
    ]
  },
  {
    "Title": "Gõ Cửa Trái Tim Karaoke Tone Nữ ( Am ) Nhạc Sống Dễ Hát | Trọng Hiếu",
    "Channel": "Hiếu Organ",
    "Views": "184428",
    "URL": "https://www.youtube.com/watch?v=7VUHoc2RVLs",
    "Image": "https://i.ytimg.com/vi/7VUHoc2RVLs/hqdefault.jpg",
    "ViewHistory": [
      184419,
      184428
    ]
  },
  {
    "Title": "Selena Gomez, benny blanco - Ojos Tristes (with The Marías) (Official Lyric Video)",
    "Channel": "SelenaGomezVEVO",
    "Views": "4990421",
    "URL": "https://www.youtube.com/watch?v=Ch6xdV_ZjdU",
    "Image": "https://i.ytimg.com/vi/Ch6xdV_ZjdU/hqdefault.jpg",
    "ViewHistory": [
      4990382,
      4990421
    ]
  },
  {
    "Title": "Bắc Bling Remix Căng Đét - Hoà Minzy, Ns Xuân Hinh, Masew Ft Tuấn Cry | Bắc Ninh Vốn Trọng Chữ Tình",
    "Channel": "H2O Remix",
    "Views": "1723899",
    "URL": "https://www.youtube.com/watch?v=nvWR2fMHrZE",
    "Image": "https://i.ytimg.com/vi/nvWR2fMHrZE/hqdefault.jpg",
    "ViewHistory": [
      1723899,
      1723899
    ]
  },
  {
    "Title": "[XHTDRLX3] Thất Tình - Anh Tú trở lại sở trường với ca khúc không thể suy hơn",
    "Channel": "FOREST STUDIO",
    "Views": "1009392",
    "URL": "https://www.youtube.com/watch?v=DbMZ8O9VVFk",
    "Image": "https://i.ytimg.com/vi/DbMZ8O9VVFk/hqdefault.jpg",
    "ViewHistory": [
      1009269,
      1009392
    ]
  },
  {
    "Title": "Em Muốn Tự Do (LUNY Remix) - Du Uyên x Thưởng | Em Anh Người Ta",
    "Channel": "LUNY Entertainment",
    "Views": "408404",
    "URL": "https://www.youtube.com/watch?v=xpxo2KVQOoA",
    "Image": "https://i.ytimg.com/vi/xpxo2KVQOoA/hqdefault.jpg",
    "ViewHistory": [
      408393,
      408404
    ]
  },
  {
    "Title": "Anh Chẳng Thể Remix (Bản Hot TikTok) - Phạm Kỳ x Xuân Tuấn Remix | Câu Tình Ca Này Không Hay Thì ...",
    "Channel": "Phương Anh Remix",
    "Views": "982542",
    "URL": "https://www.youtube.com/watch?v=zJg4Pv7Lsl0",
    "Image": "https://i.ytimg.com/vi/zJg4Pv7Lsl0/hqdefault.jpg",
    "ViewHistory": [
      982533,
      982542
    ]
  },
  {
    "Title": "Đóa Hoa - BigWind ft TeuYungBoy (prod. DONAL) | Official MV",
    "Channel": "WORKAHOLIC$",
    "Views": "1332461",
    "URL": "https://www.youtube.com/watch?v=P5bzF31Xvg4",
    "Image": "https://i.ytimg.com/vi/P5bzF31Xvg4/hqdefault.jpg",
    "ViewHistory": [
      1332448,
      1332461
    ]
  },
  {
    "Title": "Karaoke Bắc Bling Bắc Ninh - Hòa Minzy Guitar Solo Beat Acoustic | Anh Trường Guitar",
    "Channel": "Anh Trường Guitar",
    "Views": "393054",
    "URL": "https://www.youtube.com/watch?v=UJiTxdaphxo",
    "Image": "https://i.ytimg.com/vi/UJiTxdaphxo/hqdefault.jpg",
    "ViewHistory": [
      393045,
      393054
    ]
  },
  {
    "Title": "(Remix) Trưởng Thành - DIMZ | Cô gái à em đừng khóc Remix Hot TikTok",
    "Channel": "DIMZ Official",
    "Views": "221426",
    "URL": "https://www.youtube.com/watch?v=JQoUv0zrZwQ",
    "Image": "https://i.ytimg.com/vi/JQoUv0zrZwQ/hqdefault.jpg",
    "ViewHistory": [
      221421,
      221426
    ]
  },
  {
    "Title": "ĐỊA ĐÀNG - HOÀNG OANH x L2T ft DUY DONG REMIX | Nói Anh Nghe Địa Đàng Mở Cửa Là Để Chờ Bước Chân Em",
    "Channel": "ACV Entertainment",
    "Views": "742152",
    "URL": "https://www.youtube.com/watch?v=7bYd1XGcctc",
    "Image": "https://i.ytimg.com/vi/7bYd1XGcctc/hqdefault.jpg",
    "ViewHistory": [
      742078,
      742152
    ]
  }
]